LICENSE
thenet/__init__.py
thenet-0.1.0.dist-info/LICENSE
thenet-0.1.0.dist-info/WHEEL
thenet-0.1.0.dist-info/METADATA
thenet-0.1.0.dist-info/RECORD
